cytodataframe/__init__.py
cytodataframe/frame.py
cytodataframe/image.py
cytodataframe-0.0.30.dist-info/METADATA
cytodataframe-0.0.30.dist-info/WHEEL
cytodataframe-0.0.30.dist-info/licenses/LICENSE
cytodataframe-0.0.30.dist-info/RECORD
