Metadata-Version: 2.4
Name: CytoDataFrame
Version: 0.0.30
Summary: An in-memory data analysis format for single-cell profiles alongside their corresponding images and segmentation masks.
License: BSD-3-Clause
License-File: LICENSE
Author: Way Science Community
Requires-Python: >=3.10,<3.14
Classifier: License :: OSI Approved :: BSD License
Classifier: Programming Language :: Python :: 3
Classifier: Programming Language :: Python :: 3.10
Classifier: Programming Language :: Python :: 3.11
Classifier: Programming Language :: Python :: 3.12
Classifier: Programming Language :: Python :: 3.13
Requires-Dist: imagecodecs (>=2024.9.22,<2026.0.0)
Requires-Dist: imageio (>=2.37.0,<3.0.0)
Requires-Dist: ipython (>=8.12.3,<9.0.0)
Requires-Dist: ipywidgets (>=8.1.7,<9.0.0)
Requires-Dist: matplotlib (>=3.9.3,<4.0.0)
Requires-Dist: opencv-python (>=4.10.0.84,<5.0.0.0)
Requires-Dist: pandas (<2.2.2) ; python_version < "3.9"
Requires-Dist: pandas (>=2.2.2,<3.0.0) ; python_version >= "3.9"
Requires-Dist: pyarrow (>=16,<21)
Requires-Dist: pywavelets (>1.4.1) ; python_version >= "3.9"
Requires-Dist: pywavelets (>=1.4.1,<2.0.0) ; python_version < "3.9"
Requires-Dist: scikit-image (>0.19.3) ; python_version >= "3.9"
Requires-Dist: scikit-image (>=0.19.3,<0.20.0) ; python_version < "3.9"
